dora_llama_cpp_python/__init__.py
dora_llama_cpp_python/__main__.py
dora_llama_cpp_python/main.py
dora_llama_cpp_python-1.0.1.dist-info/METADATA
dora_llama_cpp_python-1.0.1.dist-info/WHEEL
dora_llama_cpp_python-1.0.1.dist-info/entry_points.txt
dora_llama_cpp_python-1.0.1.dist-info/top_level.txt
dora_llama_cpp_python-1.0.1.dist-info/RECORD
