Metadata-Version: 2.4
Name: dora-llama-cpp-python
Version: 1.0.1
Summary: dora-llama-cpp-python
Author-email: Shashwat Patil <email@email.com>
License: MIT
Requires-Python: >=3.9
Requires-Dist: dora-rs>=0.3.9
Requires-Dist: torch==2.4.0
Requires-Dist: torchvision>=0.19
Requires-Dist: torchaudio>=2.1.0
Requires-Dist: opencv-python>=4.1.1
Requires-Dist: modelscope>=1.18.1
Requires-Dist: huggingface-hub>=0.29.0
Requires-Dist: mlx-lm>=0.21.1; sys_platform == "darwin"
Requires-Dist: llama-cpp-python
